pycasta/PDB_downloader.py
pycasta/__init__.py
pycasta/alpha_shape.py
pycasta/atomic_radii.py
pycasta/cgal_wdelaunay.py
pycasta/check_pocket_stats.py
pycasta/config.py
pycasta/dual_sets.py
pycasta/find_pymol.py
pycasta/grid_search.py
pycasta/optimize_alpha.py
pycasta/ply_to_obj.py
pycasta/pocket_detection.py
pycasta/pymol_vis.py
pycasta/ranking.py
pycasta/run_analysis.py
pycasta/run_entrypoint.py
pycasta/run_find_on_all.py
pycasta/utils/__init__.py
pycasta/utils/common.py
pycasta/utils/data_utils.py
pycasta/utils/geometry_utils.py
pycasta/utils/pocket_utils.py
pycasta/utils/preprocessing_utils.py
pycasta/utils/sasa_utils.py
pycasta/validation/__init__.py
pycasta/validation/check_geometry.py
pycasta/validation/check_sasa.py
pycasta-1.0.8.dist-info/licenses/LICENSE
pycasta-1.0.8.dist-info/METADATA
pycasta-1.0.8.dist-info/WHEEL
pycasta-1.0.8.dist-info/entry_points.txt
pycasta-1.0.8.dist-info/top_level.txt
pycasta-1.0.8.dist-info/RECORD
