Metadata-Version: 2.4
Name: pycasta
Version: 1.0.8
Summary: PyCAST: Pocket detection and validation in proteins
Author-email: Giorgio <giorgio@gmail.com>
License: MIT
Requires-Python: >=3.8
License-File: LICENSE
Requires-Dist: numpy
Requires-Dist: scipy
Requires-Dist: pandas
Requires-Dist: matplotlib
Requires-Dist: biopython
Requires-Dist: scikit-learn
Requires-Dist: tabulate
Requires-Dist: plyfile
Requires-Dist: trimesh
Requires-Dist: openpyxl
Dynamic: license-file
